cpc.stats-1.3.5-py2.7-nspkg.pth
cpc/stats/__init__.py
cpc/stats/stats.py
cpc.stats-1.3.5.dist-info/DESCRIPTION.rst
cpc.stats-1.3.5.dist-info/METADATA
cpc.stats-1.3.5.dist-info/RECORD
cpc.stats-1.3.5.dist-info/WHEEL
cpc.stats-1.3.5.dist-info/metadata.json
cpc.stats-1.3.5.dist-info/namespace_packages.txt
cpc.stats-1.3.5.dist-info/top_level.txt
