Metadata-Version: 2.0
Name: cpc.stats
Version: 1.3.5
Summary: Set of utilities to perform statistical calculations
Home-page: https://www.github.com/noaa-nws-cpc/cpc.stats.git
Author: Melissa Ou
Author-email: melissa.ou@noaa.gov
License: CC
Platform: UNKNOWN
Classifier: Development Status :: 1 - Planning
Classifier: Environment :: Console
Classifier: Intended Audience :: Science/Research
Classifier: Programming Language :: Python
Classifier: Programming Language :: Python :: 3
Classifier: Operating System :: OS Independent
Classifier: Topic :: Scientific/Engineering :: Atmospheric Science
Classifier: License :: CC0 1.0 Universal (CC0 1.0) Public Domain Dedication
Requires-Dist: numpy
Requires-Dist: scipy
